README.md
setup.py
leveling/__init__.py
leveling/core/__init__.py
leveling/core/overrider.py
leveling/core/delegate/__init__.py
leveling/core/delegate/print.py
leveling/core/error/BuiltinLockedError.py
leveling/core/error/__init__.py
leveling/core/lock/List.py
leveling/core/lock/Locked.py
leveling/core/lock/Locking.py
leveling/core/lock/__init__.py
leveling/lang/__init__.py
leveling/lang/zh_cn.py
youshallnotuseit/__init__.py
youshallnotuseit.egg-info/PKG-INFO
youshallnotuseit.egg-info/SOURCES.txt
youshallnotuseit.egg-info/dependency_links.txt
youshallnotuseit.egg-info/top_level.txt
youshallnotuseit/covers/Exceptions.py
youshallnotuseit/covers/Functions.py
youshallnotuseit/covers/Lang.py
youshallnotuseit/covers/Types.py
youshallnotuseit/covers/__init__.py
youshallnotuseit/magicians/Banning.py
youshallnotuseit/magicians/Locking.py
youshallnotuseit/magicians/Overrider.py
youshallnotuseit/magicians/__init__.py