Metadata-Version: 2.1
Name: youshallnotuseit
Version: 0.1.0
Summary: Tools to lock/unlock/fully waste python's built in function/types
Home-page: https://github.com/FCWYzzr/YouShallNotUseIt
Author: FCWYzzr
Author-email: fcwyzzr@163.com
License: MIT
Classifier: License :: OSI Approved :: MIT License
Classifier: Programming Language :: Python
Classifier: Programming Language :: Python :: 3
Classifier: Programming Language :: Python :: 3.6
Classifier: Programming Language :: Python :: Implementation :: CPython
Classifier: Programming Language :: Python :: Implementation :: PyPy
Requires-Python: >=3.11.0
